ethiobank_receipts/__init__.py
ethiobank_receipts/cli.py
ethiobank_receipts/download.py
ethiobank_receipts/extractors/awash.py
ethiobank_receipts/extractors/boa.py
ethiobank_receipts/extractors/cbe.py
ethiobank_receipts/extractors/dashen.py
ethiobank_receipts/extractors/tele.py
ethiobank_receipts/extractors/zemen.py
ethiobank_receipts-0.1.1.dist-info/METADATA
ethiobank_receipts-0.1.1.dist-info/WHEEL
ethiobank_receipts-0.1.1.dist-info/entry_points.txt
ethiobank_receipts-0.1.1.dist-info/top_level.txt
ethiobank_receipts-0.1.1.dist-info/RECORD
