Metadata-Version: 2.4
Name: ethiobank-receipts
Version: 0.1.1
Summary: Optimized receipt extraction for Ethiopian banks using connection pooling
Author: Nahom Alemu
License: MIT
Project-URL: Homepage, https://github.com/NahomAl/ethiobank_receipts
Project-URL: Source, https://github.com/NahomAl/ethiobank_receipts
Project-URL: Bug Tracker, https://github.com/NahomAl/ethiobank_receipts/issues
Requires-Python: >=3.8
Requires-Dist: requests
Requires-Dist: pdfplumber
Requires-Dist: beautifulsoup4
Requires-Dist: selenium
Requires-Dist: urllib3
Provides-Extra: dev
Requires-Dist: pytest; extra == "dev"
Requires-Dist: black; extra == "dev"
Requires-Dist: flake8; extra == "dev"
